starepandas/__init__.py
starepandas/_version.py
starepandas/staredataframe.py
starepandas/stareseries.py
starepandas/datasets/__init__.py
starepandas/io/__init__.py
starepandas/io/database.py
starepandas/io/folder.py
starepandas/io/geotiff.py
starepandas/io/pod.py
starepandas/io/postgis.py
starepandas/io/s3.py
starepandas/io/granules/__init__.py
starepandas/io/granules/atms.py
starepandas/io/granules/granule.py
starepandas/io/granules/imergl3.py
starepandas/io/granules/modis.py
starepandas/io/granules/ssmis.py
starepandas/io/granules/viirsl2.py
starepandas/tools/__init__.py
starepandas/tools/adjust_workers.py
starepandas/tools/spatial_conversions.py
starepandas/tools/stare_join.py
starepandas/tools/temporal_conversions.py
starepandas/tools/trixel_conversions.py
tests/__init__.py
tests/test_catalog.py
tests/test_ccw.py
tests/test_conversions.py
tests/test_dissolve.py
tests/test_enclaves.py
tests/test_geotiff.py
tests/test_guess_companion_path.py
tests/test_instantiation.py
tests/test_intersects.py
tests/test_join.py
tests/test_na.py
tests/test_parallel.py
tests/test_plotting.py
tests/test_readgranules.py
tests/test_resolution.py
tests/test_ring_lookup.py
tests/test_shapely20.py
tests/test_trixels.py
tests/test_type_persistance.py
starepandas-0.6.8.dist-info/LICENSE
starepandas-0.6.8.dist-info/METADATA
starepandas-0.6.8.dist-info/WHEEL
starepandas-0.6.8.dist-info/top_level.txt
starepandas-0.6.8.dist-info/RECORD
