Metadata-Version: 2.2
Name: starepandas
Version: 0.6.8
Summary: STARE pandas extensions
Home-page: https://github.com/SpatioTemporal/STAREPandas
Author: Niklas Griessbaum
Author-email: griessbaum@ucsb.edu
Project-URL: Bug Tracker, https://github.com/SpatioTemporal/STAREPandas/issues
Classifier: Programming Language :: Python :: 3
Classifier: License :: OSI Approved :: MIT License
Classifier: Operating System :: OS Independent
Requires-Python: >=3.12
License-File: LICENSE
Requires-Dist: numpy>=2.2.1
Requires-Dist: geopandas>=0.14.0
Requires-Dist: shapely>=2.0
Requires-Dist: pandas>=2.0.3
Requires-Dist: dask>=2025.1.0
Requires-Dist: distributed>=2022.9.0
Requires-Dist: cartopy>=0.22.0
Requires-Dist: pystare>=0.8.14
Requires-Dist: h5py>=3.7.0
Requires-Dist: pyarrow>=19.0.0
Requires-Dist: pyhdf>=0.10.5
Requires-Dist: netCDF4>=1.5.8
Requires-Dist: boto3>=1.23.10
Requires-Dist: astropy>=7.0.0
Requires-Dist: matplotlib>=3.5.2
Requires-Dist: rasterio>=1.3.0
Requires-Dist: xarray>=2022.6.0
Requires-Dist: rtree>=1.0.0
Requires-Dist: scipy>=1.9.1
Requires-Dist: puremagic>=1.14
Requires-Dist: sqlalchemy>=2.0.18
Requires-Dist: GeoAlchemy2>=0.14.0
Requires-Dist: psycopg2>=2.9.6
